cli/__init__.py
cli/ai_client.py
cli/config.py
cli/explainer.py
cli/git_handler.py
cli/main.py
clai_ai-0.1.6.dist-info/METADATA
clai_ai-0.1.6.dist-info/WHEEL
clai_ai-0.1.6.dist-info/entry_points.txt
clai_ai-0.1.6.dist-info/top_level.txt
clai_ai-0.1.6.dist-info/RECORD
