Metadata-Version: 2.4
Name: clai-ai
Version: 0.1.6
Summary: Add your description here
Requires-Python: >=3.12
Requires-Dist: click>=8.2.1
Requires-Dist: gitpython>=3.1.44
Requires-Dist: google-genai>=1.20.0
Requires-Dist: python-dotenv>=1.1.0
Requires-Dist: twine>=6.1.0
Requires-Dist: typer>=0.16.0
